{
    "students": [
        {
            "firstName": "Harsha",
            "dob": "1999-03-15",
        
            "addresses": [ 
                {
                    "type": "perm",
                    "flatNumber": 104,
                    "street": "gandhi nagar",
                    "city": "hyderabad"
                },
                {
                    "type" : "current",
                    "flatNumber": 104,
                    "street": "gandhi nagar",
                    "city": "hyderabad"
                }
            ],
            "skills": ["java", "devops", "cloud"]
        },
        {
            "firstName": "Harsha",
            "dob": "1999-03-15",
        
            "addresses": [ 
                {
                    "type": "perm",
                    "flatNumber": 104,
                    "street": "gandhi nagar",
                    "city": "hyderabad"
                },
                {
                    "type" : "current",
                    "flatNumber": 104,
                    "street": "gandhi nagar",
                    "city": "hyderabad"
                }
            ],
            "skills": ["java", "devops", "cloud"]
        }
    ]
}